actuation/__init__.py
actuation-0.0.0.dist-info/METADATA
actuation-0.0.0.dist-info/WHEEL
actuation-0.0.0.dist-info/top_level.txt
actuation-0.0.0.dist-info/RECORD
