Metadata-Version: 2.4
Name: actuation
Version: 0.0.0
Summary: Coming soon
Author-email: Stardust Research <engineering@stardustresarch.com>
